sub_package1/__init__.py
sub_package1-1.0.dist-info/LICENSE
sub_package1-1.0.dist-info/METADATA
sub_package1-1.0.dist-info/WHEEL
sub_package1-1.0.dist-info/top_level.txt
sub_package1-1.0.dist-info/RECORD
